netapp_ontap/__init__.py
netapp_ontap/__main__.py
netapp_ontap/config.py
netapp_ontap/error.py
netapp_ontap/host_connection.py
netapp_ontap/py.typed
netapp_ontap/resource.py
netapp_ontap/resource_table.py
netapp_ontap/response.py
netapp_ontap/utils.py
netapp_ontap/validations.py
netapp_ontap/docs/config.html
netapp_ontap/docs/error.html
netapp_ontap/docs/host_connection.html
netapp_ontap/docs/index.html
netapp_ontap/docs/resource.html
netapp_ontap/docs/resource_table.html
netapp_ontap/docs/response.html
netapp_ontap/docs/utils.html
netapp_ontap/docs/validations.html
netapp_ontap/docs/models/account_application.html
netapp_ontap/docs/models/acl.html
netapp_ontap/docs/models/acl_delete.html
netapp_ontap/docs/models/ad_domain.html
netapp_ontap/docs/models/ad_domain_svm.html
netapp_ontap/docs/models/advanced_rights.html
netapp_ontap/docs/models/aggregate_block_storage.html
netapp_ontap/docs/models/aggregate_block_storage_hybrid_cache.html
netapp_ontap/docs/models/aggregate_block_storage_mirror.html
netapp_ontap/docs/models/aggregate_block_storage_primary.html
netapp_ontap/docs/models/aggregate_cloud_storage.html
netapp_ontap/docs/models/aggregate_data_encryption.html
netapp_ontap/docs/models/aggregate_inactive_data_reporting.html
netapp_ontap/docs/models/aggregate_patch.html
netapp_ontap/docs/models/aggregate_space.html
netapp_ontap/docs/models/aggregate_space_block_storage.html
netapp_ontap/docs/models/aggregate_space_cloud_storage.html
netapp_ontap/docs/models/aggregate_spare.html
netapp_ontap/docs/models/aggregate_warning.html
netapp_ontap/docs/models/aggregate_warning_action.html
netapp_ontap/docs/models/aggregate_warning_warning.html
netapp_ontap/docs/models/analytics_collection_info.html
netapp_ontap/docs/models/analytics_collection_info_by_accessed_time.html
netapp_ontap/docs/models/analytics_collection_info_by_accessed_time_bytes_used.html
netapp_ontap/docs/models/analytics_collection_info_by_modified_time.html
netapp_ontap-9.9.1.0.dist-info/LICENSE
netapp_ontap-9.9.1.0.dist-info/METADATA
netapp_ontap-9.9.1.0.dist-info/WHEEL
netapp_ontap-9.9.1.0.dist-info/entry_points.txt
netapp_ontap-9.9.1.0.dist-info/top_level.txt
netapp_ontap-9.9.1.0.dist-info/RECORD
