Metadata-Version: 2.1
Name: netapp-ontap
Version: 9.9.1.0
Summary: A library for working with ONTAP's REST APIs simply in Python
Home-page: https://devnet.netapp.com/restapi.php
Author: NetApp
Author-email: ng-ontap-rest-python-lib@netapp.com
License: UNKNOWN
Project-URL: Documentation, https://library.netapp.com/ecmdocs/ECMLP2874673/html/index.html
Keywords: NetApp ONTAP REST API development
Platform: UNKNOWN
Classifier: Programming Language :: Python :: 3.5
Classifier: License :: OSI Approved :: BSD License
Classifier: Operating System :: OS Independent
Requires-Python: >=3.5
Requires-Dist: marshmallow (>=3.2.1)
Requires-Dist: requests (>=2.22.0)
Requires-Dist: requests-toolbelt (>=0.9.1)
Requires-Dist: urllib3 (>=1.25.11)
Provides-Extra: cli
Requires-Dist: cliche (>=2020.4) ; extra == 'cli'
